serra/__init__.py
serra/aws.py
serra/base.py
serra/cli.py
serra/config.py
serra/config_parser.py
serra/databricks.py
serra/exceptions.py
serra/profile.py
serra/run.py
serra/spark.py
serra/tests.py
serra/utils.py
serra/data/autocomplete/README.md
serra/data/autocomplete/gen_schemas.py
serra/data/autocomplete/inputs/specs.json
serra/data/autocomplete/output/AddColumnTransformer.json
serra/data/autocomplete/output/AggregateTransformer.json
serra/data/autocomplete/output/AmazonS3Reader.json
serra/data/autocomplete/output/AmazonS3Writer.json
serra/data/autocomplete/output/BigQueryReader.json
serra/data/autocomplete/output/BigQueryWriter.json
serra/data/autocomplete/output/CaseWhenTransformer.json
serra/data/autocomplete/output/CastColumnTransformer.json
serra/data/autocomplete/output/CoalesceTransformer.json
serra/data/autocomplete/output/CrossJoinTransformer.json
serra/data/autocomplete/output/DatabricksReader.json
serra/data/autocomplete/output/DatabricksWriter.json
serra/data/autocomplete/output/DateTruncTransformer.json
serra/data/autocomplete/output/DropColumnTransformer.json
serra/data/autocomplete/output/FilterTransformer.json
serra/data/autocomplete/output/GeoDistanceTransformer.json
serra/data/autocomplete/output/GetCountTransformer.json
serra/data/autocomplete/output/GetDistinctTransformer.json
serra/data/autocomplete/output/GetMaxOrMinTransformer.json
serra/data/autocomplete/output/ImputeTransformer.json
serra/data/autocomplete/output/JoinTransformer.json
serra/data/autocomplete/output/JoinWithConditionTransformer.json
serra/data/autocomplete/output/LocalReader.json
serra/data/autocomplete/output/LocalWriter.json
serra/data/autocomplete/output/MapTransformer.json
serra/data/autocomplete/output/MultiJoinTransformer.json
serra/data/autocomplete/output/MultipleCaseWhenTransformer.json
serra/data/autocomplete/output/OrderByTransformer.json
serra/data/autocomplete/output/PivotTransformer.json
serra/data/autocomplete/output/RenameColumnTransformer.json
serra-0.7.198.dist-info/LICENSE.md
serra-0.7.198.dist-info/METADATA
serra-0.7.198.dist-info/WHEEL
serra-0.7.198.dist-info/entry_points.txt
serra-0.7.198.dist-info/top_level.txt
serra-0.7.198.dist-info/RECORD
